finance_dl/__init__.py
finance_dl/amazon.py
finance_dl/anthem.py
finance_dl/chromedriver_wrapper.py
finance_dl/cli.py
finance_dl/comcast.py
finance_dl/csv_merge.py
finance_dl/discover.py
finance_dl/ebmud.py
finance_dl/gemini.py
finance_dl/google_login.py
finance_dl/google_purchases.py
finance_dl/google_takeout.py
finance_dl/healthequity.py
finance_dl/mint.py
finance_dl/ofx.py
finance_dl/ofx_rename.py
finance_dl/paypal.py
finance_dl/pge.py
finance_dl/radiusbank.py
finance_dl/schwab.py
finance_dl/scrape_lib.py
finance_dl/stockplanconnect.py
finance_dl/ultipro_google.py
finance_dl/update.py
finance_dl/usbank.py
finance_dl/venmo.py
finance_dl/waveapps.py
finance_dl-1.3.4.dist-info/LICENSE
finance_dl-1.3.4.dist-info/METADATA
finance_dl-1.3.4.dist-info/WHEEL
finance_dl-1.3.4.dist-info/entry_points.txt
finance_dl-1.3.4.dist-info/top_level.txt
finance_dl-1.3.4.dist-info/RECORD
