Metadata-Version: 2.1
Name: finance-dl
Version: 1.3.4
Summary: Tools for scraping personal financial data.
Home-page: https://github.com/jbms/finance-dl
Author: Jeremy Maitin-Shepard
Author-email: jeremy@jeremyms.com
License: GPLv2
Platform: UNKNOWN
Requires-Python: >=3.5
License-File: LICENSE
Requires-Dist: bs4
Requires-Dist: mintapi >=1.31
Requires-Dist: ofxclient
Requires-Dist: selenium
Requires-Dist: ipython
Requires-Dist: selenium-requests
Requires-Dist: chromedriver-binary
Requires-Dist: beancount >=2.1.2
Requires-Dist: atomicwrites >=1.3.0
Requires-Dist: jsonschema
Requires-Dist: python-dateutil
